myfunctions/__init__.py
myfunctions/client.py
myfunctions/json_manager.py
myfunctions-0.0.2.dist-info/LICENSE
myfunctions-0.0.2.dist-info/METADATA
myfunctions-0.0.2.dist-info/WHEEL
myfunctions-0.0.2.dist-info/top_level.txt
myfunctions-0.0.2.dist-info/RECORD
