Metadata-Version: 2.1
Name: myfunctions
Version: 0.0.2
Author: unixtux
License: GNU GENERAL PUBLIC LICENSE
Requires-Python: >=3.8
License-File: LICENSE
Requires-Dist: aiotgm
